{
  "row_00": [
    "Sl. No.",
    "Particular",
    "mn",
    "Rate",
    "Rate"
  ],
  "row_01": [
    "Sl. No.",
    "Particular",
    "My",
    "Estimate",
    "Quoted"
  ],
  "row_02": [
    "1",
    "Sand 35",
    "30.00",
    "35.00",
    "32.00"
  ],
  "row_03": [
    "1",
    "Sand 45",
    "20.00",
    "45.00",
    "44.00"
  ],
  "row_04": [
    "2",
    "Cement",
    "50.00",
    "260.00",
    "251.00"
  ],
  "row_05": [
    "3.",
    "Brick",
    "1000.00",
    "5.00",
    "4.50"
  ],
  "row_06": [
    "4",
    "Metal",
    "5.00",
    "6000.00",
    "55000.00"
  ]
}